ipython_nord_theme/__about__.py
ipython_nord_theme/__init__.py
ipython_nord_theme/_version.py
ipython_nord_theme/magic.py
ipython_nord_theme/startup.py
ipython_nord_theme-0.1.0.dist-info/LICENSE
ipython_nord_theme-0.1.0.dist-info/METADATA
ipython_nord_theme-0.1.0.dist-info/WHEEL
ipython_nord_theme-0.1.0.dist-info/entry_points.txt
ipython_nord_theme-0.1.0.dist-info/top_level.txt
ipython_nord_theme-0.1.0.dist-info/RECORD
