Metadata-Version: 2.1
Name: ipython-nord-theme
Version: 0.1.0
Summary: An arctic, north-bluish theme for the IPython interactive prompt.
Home-page: https://github.com/lewisacidic/ipython-nord-theme
Author: Rich Lewis
Author-email: opensource@richlew.is
License: MIT license
Download-URL: https://github.com/lewisacidic/ipython-nord-theme/releases
Project-URL: Trackers, https://github.com/lewisacidic/ipython-nord-theme/issues
Project-URL: Source, https://github.com/lewisacidic/ipython-nord-theme
Keywords: ipython,theme,nord
Platform: UNKNOWN
Classifier: Development Status :: 2 - Pre-Alpha
Classifier: Programming Language :: Python :: 3
Classifier: Programming Language :: Python :: 3 :: Only
Classifier: Programming Language :: Python :: 3.7
Classifier: Natural Language :: English
Requires-Dist: ipython
Requires-Dist: nord-pygments
Provides-Extra: dev
Requires-Dist: ipython ; extra == 'dev'
Requires-Dist: black ; extra == 'dev'
Requires-Dist: rope ; extra == 'dev'
Requires-Dist: pre-commit ; extra == 'dev'
Requires-Dist: flake8 ; extra == 'dev'
Requires-Dist: flake8-black ; extra == 'dev'
Requires-Dist: flake8-bandit ; extra == 'dev'
Requires-Dist: flake8-bugbear ; extra == 'dev'
Requires-Dist: flake8-builtins ; extra == 'dev'
Requires-Dist: flake8-mutable ; extra == 'dev'
Requires-Dist: flake8-print ; extra == 'dev'
Requires-Dist: pep8-naming ; extra == 'dev'
Requires-Dist: pytest ; extra == 'dev'
Requires-Dist: pytest-cov ; extra == 'dev'
Provides-Extra: hook
Requires-Dist: ipython-startup-hook ; extra == 'hook'
Provides-Extra: lint
Requires-Dist: flake8 ; extra == 'lint'
Requires-Dist: flake8-black ; extra == 'lint'
Requires-Dist: flake8-bandit ; extra == 'lint'
Requires-Dist: flake8-bugbear ; extra == 'lint'
Requires-Dist: flake8-builtins ; extra == 'lint'
Requires-Dist: flake8-mutable ; extra == 'lint'
Requires-Dist: flake8-print ; extra == 'lint'
Requires-Dist: pep8-naming ; extra == 'lint'
Provides-Extra: test
Requires-Dist: pytest ; extra == 'test'
Requires-Dist: pytest-cov ; extra == 'test'
